{"684 color themes and more special themes, customized support":"684 kleurenthema's en andere speciale thema's, persoonlijke ondersteuning","About":"over","Academic":"academicus","Accept invite":"Uitnodiging accepteren","Accept request":"Verzoek accepteren","Access authority":"Toegangsprincipe","Account":"rekening","Add":"bijvoegsel","Add device":"Voeg een APPARAAT toe","Add new member successfully":"Voeg een nieuw lid toe","Admin":"administrateur","Admins and moderators":"Managers en coördinatoren","Air conditioner":"Airconditioner","Album":"album","Albums public":"De albums zijn openbaar","All":"Oke","All in RWD, cross platform support":"Alles in responsief webontwerp, ondersteuning voor meerdere platforms","Already have an account":"U heeft al een account","Amount":"bedrag","Anniv":"verjaardag","Api":"API","App":"APP","Application has failed":"toepassing is mislukt","Are you sure":"U bent zeker","Assistant":"assistent","Auto control and remote control":"Automatische bediening en afstandsbediening","Avatar":"avatar","Avatar, Cover, Background":"Avatar, dekking, achtergrond","Bachelor degree":"Bachelordiploma","Background":"record","Become friend":"om een vriend te worden","Beginning of the dream":"Het begin van de droom","Birthday":"verjaardag","Blacklist":"verbod","Buy Tranquility smart home devices, please contact me":"Koop slimme huishoudelijke apparaten, neem contact met mij op","Calendar":"kalender","Calls":"calling","Cancel":"frustratie","Cancel friend request":"vriendschapsverzoek annuleren","Cancel group request successfully":"Annuleer groepsverzoek succesvol","Cancel invite":"Uitnodiging annuleren","Cancel request successfully":"Verzoek succesvol annuleren","Cancelled":"geannuleerd","Change password":"Wachtwoord gewijzigd","Cloud":"wolk","Cloud storage":"Cloud opslag","Codes":"codes","Color me you dont need to care how much people like it":"Verf mij: het maakt u niet uit hoeveel mensen u leuk vindt","Comment":"commentaar","Comment failed":"Reactie mislukt","Comment successfully":"Reactie succesvol","Confirm":"Ik bevestig","Contact":"Neem contact met ons op","Content":"inhoud","Copy To Clipboard":"Kopiëren naar klembord","Counter":"meter","Cover":"deksel","Create":"Ik creëer","Create album":"Maak een album","Create group":"Creëer een GROEP","Create new album":"Maak een nieuw album","Create successfully":"Maak succesvol","Current city":"Woonplaats","Current city and home town":"Huidige stad: plaats van herkomst","Current live":"beek","Custom list":"Aangepaste lijst","Custom news":"Speciaal nieuws","Dashboard":"dashboard","Deadline":"tijdslimiet","Delete":"verwijderen","Delete successfully":"Met succes verwijderen","Description":"beschrijving","Device":"inrichting","Disable searching your name":"Schakel het zoeken naar uw naam uit","Discover":"Ik kom erachter","Discussion":"bespreking","Do you know":"Weet je wel","Doctoral degree":"Doctoraat","Dont have an account":"U heeft nog geen account","Door":"met","Download":"Download","E-book":"E-book","E-mail":"E-mail","Edit":"uitwerking","Education":"opleiding","Education is what remains after one has forgotten everything he/she learned in school":"Onderwijs is wat overblijft nadat iemand alles is vergeten wat hij op school heeft geleerd","Elementary school":"Lagere school","Email":"ELEKTRONISCH ADRES","Emoji":"Emoji","Error":"fout","Fan pages":"Fanpagina's","Favorite":"liefje","Favorite trip":"Favoriete reis","Favorited successfully":"Favoriet met succes","Feature":"kenmerken","Feedback":"terugkoppeling","Feedback or suggestion":"Opmerkingen of suggesties","File":"file","Files transfer messages":"Bestandsoverdracht, Berichten","Folder":"map","Friend":"vriend","Friend Requests":"Vriendschapsverzoeken","Friend list":"Vriendenlijst","Friend request":"Vriendschapsverzoek","Friend request sent successfully":"Vriendverzoek succesvol verzonden","Fullscreen for the best experience":"Volledig scherm voor de beste ervaring","Game":"spel","General":"algemeen","Give your album a special name":"Geef je album een speciale naam","Global weather":"Wereld weer","Go to the settings page to find a favorite app":"Ga naar de instellingenpagina om een favoriete app te vinden","Great dashboard UI":"Geweldige gebruikersinterface van instrumentenpaneel","Group name":"Groepsnaam","Groups":"groepen","Health":"gezondheid","High quality image support":"Hoge kwaliteit beeldondersteuning","Humidity":"vocht","I have not artificial intelligence yet, I will serve you soon":"Ik heb nog geen kunstmatige intelligentie, ik zal je snel van dienst zijn","If you are interested in it please contact me":"Neem contact met me op als je interesse hebt","Image":"afbeelding","Information public":"De informatie is openbaar","Interested in":"Ik ben geïnteresseerd in","Introduction":"introductie","Invite":"Ik nodig je uit","Io":"IO","IoT, easy connect everything":"IoT, gemakkelijke verbinding voor iedereen","It is not supported yet":"Nog niet ondersteund","It is the basic quota Ideal for a normal user and experimenting with this personal assistant system":"Het is het basisquotum. Ideaal voor een gewone gebruiker en experimenteer met dit persoonlijke assistentsysteem","It's IOT device, you can put it everywhere, and getting humidy, temperature, even remote control power":"Het is een IoT-apparaat, u kunt het overal aansluiten en vocht, temperatuur en zelfs de afstandsbediening gebruiken","Job":"baan","Join":"deelname","Join us":"kom met ons mee","Junior college":"Junior College","Junior high school":"Middelbare school","Lamp":"lamp","Language":"taal","Let us talk":"Laten we praten","Lightroom":"Lightroom","Link":"link","Live":"Ik leef","Lobby":"hal","Location":"plaats","Login":"verbinding","Logout":"ontkoppeling","Logs":"logs","Love this system, this is a good choice":"Ben dol op dit systeem, dit is een goede keuze","Master degree":"Postgraduaat","Media":"BEDRIJFS MEDIA","Medicine":"drug","Meeting":"bijeenkomst","Members":"leden","More apps coming soon":"binnenkort meer applicaties","More powerful":"Krachtiger","Multiple languages support":"Ondersteuning in meerdere talen","Muse":"muze","Music":"MUSIC","Mutil room mutil user support":"Ondersteuning voor Mutil-Room, Mutil-User","Mutil version(original version, cover version)":"Mutil-versie (originele versie, omslagversie)","My note":"Mijn notitie","My paper":"Mijn krant","My trip":"Mijn reis","Name":"naam","News":"nieuws","Nickname":"bijnaam","No":"niet","No data found":"Geen gegevens gevonden","No friend":"Er is geen vriend","No notification":"Er is geen melding","No poll":"Er is geen peiling","No public post":"Er is geen openbare plaatsing","No task":"Er is geen plicht","Non-friends can invite to join a new group":"Niet-vrienden kunnen worden uitgenodigd om lid te worden van een nieuwe groep","Note":"noot","Notifications":"meldingen","Now":"nu","Office":"kantoor","Online custom news":"Speciaal nieuws op internet","Online status":"Email status","Only me":"Alleen ik","Open":"geopend","Other":"anders","Overview":"GEBIED BEELD","Paper":"papier","Participants":"deelnemers","Password":"wachtwoord","Password must be at least 6 characters":"Het wachtwoord moet minimaal 6 tekens lang zijn","Password not match":"Het wachtwoord komt niet overeen","Password(at least 6 characters)":"Wachtwoord (minimaal 6 tekens)","Pending review":"In afwachting van beoordeling","Photos":"foto's","Pin":"broche","Place":"plaats","Places lived":"Feesten leefden","Planned spending":"Geplande uitgaven","Please enter access code":"Voer je wachtwoord in","Please fill in required fields":"Vul de verplichte velden in","Pm25":"PM2.5","Poll":"poll","Post":"plaats","Posts public":"ambtenarenposten","Preschool":"voorschoolse","Privacy":"geheimhouding","Product":"product","Profile":"profile","Project":"project","Public":"publiek","Random":"toevallig","Re-password":"heraansluiting","Read more":"Lees meer","Recommend for you soon, but not this day":"We raden je snel aan, maar niet vandaag","Register":"Ik registreer","Reject friend request":"vriendschapsverzoek weigeren","Reject request":"Afwijzing van aanvraag","Related":"Ik ben familie van","Relationship":"verhouding","Remove Favorited":"Favorieten verwijderen","Remove a member":"Verwijder één lid","Remove a member successfully":"Verwijder een lid met succes","Rename":"Ik hernoem het","Rename successfully":"Naam succesvol wijzigen","Replied":"antwoordde hij","Report":"VERWIJZEN","Robot":"robot","Score":"partituur","Search":"zoektocht","Secret":"geheim","Security":"veiligheid","Send":"gekwetter","Send group request successfully":"Groepsverzoek succesvol verzonden","Send invite":"Uitnodiging verzenden","Send join group request":"verzoek tot lidmaatschap verzenden","Send request":"Verzoek verzenden","Senior high school":"Middelbare school","Serial Number":"Serienummer","Server":"dienaar","Setting":"synthese","Share":"aandeel","Signup":"Meld je aan","Single":"single","Slider":"schuif","Social":"sociaal","Social network":"Sociaal netwerk","Start":"begin","Status":"conditie","Storage":"opslagruimte","Store":"winkel","Studied at":"Ik heb gestudeerd aan","Success":"succes","Support":"ondersteuning","Sync":"timing","System":"systeem","TQ2ME is one of Tranquility applications for URL Shortener":"TQ2ME is een van de Tranquility-toepassingen voor de verkortings-URL","Tag":"label","Taken":"nemen","Task":"project","Tell others what this group is about":"Vertel anderen wat deze groep is","Temperature":"temperatuur","Terms":"voorwaarden","Text Editor":"Tekstverwerker","Text something":"iets tekst","Themes":"thema's","No posts to show":"Er zijn geen berichten om weer te geven","Timeline":"dienstregeling","Timer":"uur","Title":"titel","Toaster":"toaster","Tools":"gereedschap","Total balance":"Totaal saldo","Tran":"Tran","Tranquility addictions best choice":"Regelmatige verslavingen betere keuze","Tranquility is the personal assistant system, making everything as simple as possible":"Stilte is het persoonlijke hulpsysteem, dat alles zo eenvoudig mogelijk maakt","Translate":"vertalen","Trip":"trip","Tv":"TV","URL format error":"URL-formaatfout","Untitled":"Untitled","Update":"Ik moderniseer","Update failed":"Update mislukt","Update successful":"De update was succesvol","Updated":"UPDATE","Upload":"Upload","User":"gebruiker","User hide all albums":"De gebruiker verbergt alle albums","User hide all information":"De gebruiker verbergt alle informatie","User hide all posts":"De gebruiker verbergt alle berichten","Username is already taken!":"Gebruikersnaam al in gebruik!","Username must be 1-20 characters":"De gebruikersnaam moet 1-20 tekens lang zijn","Username only allowed in English":"De gebruikersnaam is alleen toegestaan in het Engels","Username or password is incorrect!":"Onjuiste gebruikersnaam of wachtwoord!","Video":"video","View sent requests":"Bekijk verzonden verzoeken","Vocational high school":"Professionele middelbare school","Wallet":"portemonnee","We have over 120 news and counting so far":"We hebben tot nu toe meer dan 120 nieuws en tellen","Welcome to":"Welkom bij","What is on your mind":"Wat denk jij","Why":"waarom","Work":"baan","Work and education":"Werk en opleiding","Yes":"ja","You are not":"Dat ben je niet","You are not a member of":"U bent geen lid van","You can not use system default name":"U kunt de standaardsysteemnaam niet gebruiken","You look like need extra quota, is not it":"Je ziet eruit alsof je een extra quotum nodig hebt, nietwaar?","You want to join":"Wil je lid worden?","You wont be able to revert this":"U kunt dit niet herstellen","Your albums are safe":"Je album is veilig","Your data is safe":"Uw gegevens zijn veilig","Your email?":"Uw e-mailadres","Your post are safe":"Je bericht is veilig","Select":"Ik kies","Make everything as simple as possible":"Maak alles zo eenvoudig mogelijk","Short URL":"Korte URL","Social, work, entertainment, all in personal systems":"Sociaal, werk, plezier, alles in persoonlijke systemen","Share the world":"Deel de wereld","Modern UI and powerful features":"Moderne gebruikersinterface en krachtige functies","More apps and surprises waiting for you to discover":"Meer toepassingen en verrassingen wachten op u om te ontdekken","Easily connect to the Internet of Things":"Maak eenvoudig verbinding met het internet der dingen","Give me some feedback or suggestions, I am continually improving system to provide the great Tranquility experience":"Geef me enkele opmerkingen of suggesties. Ik blijf het systeem verbeteren om de ervaring van Great Darkness te bieden.","Delete album":"Album verwijderen","Schedule":"programma","Color":"kleur","No plan in this date":"Er is geen plan op deze datum","No activities today":"Er zijn geen activiteiten vandaag","No description":"Geen omschrijving","Upload failure":"Kan niet laden","Upload success":"Upload succes","The default album cannot be deleted":"Het standaardalbum kan niet worden verwijderd","Have already commented it":"Ze hebben er al commentaar op gegeven","Accept":"Ik accepteer het","Reject":"Ik wijs af","Follow":"Volgen","Following":"NEXT","Please login to continue":"Log in om door te gaan","Cancel follow":"Annuleren volgen","Add to playlists":"Toevoegen aan afspeellijst","Switch commenter":"Wijzig commenter","Web":"weefsel","Forgot password":"Wachtwoord vergeten?","Wrong email":"Verkeerde e-mail","The system was unable to find a matching Tranquility Account based on the information you provided":"Het systeem kon geen overeenkomstig bewegend account vinden op basis van de door u verstrekte informatie","Recover Password":"Wachtwoord herstel","An email has been sent":"Er is een e-mail verzonden","New password":"Nieuw wachtwoord","Time":"tijd","No search results found":"Geen zoekresultaten gevonden","Unknown members":"Onbekende leden","Display members on group card":"Toon leden op de groepskaart","Maximum file size is 100MB":"De maximale bestandsgrootte is 100 MB","Place you have lived":"Een plaats waar je gewoond hebt","Basic information":"Basis informatie","Social links":"Sociale banden","Well done":"Goed gedaan","Good job":"Goed gedaan","Bravo":"Goed gedaan","Nice":"mooi","People you may know":"Mensen die je waarschijnlijk kent","Messenger":"boodschapper","Please add content or image":"Voeg inhoud of afbeelding toe","Connect over 109 countries users":"Log in bij 109 gebruikerslanden","Get breaking news headlines, global weather forecast, and search for articles from over 30,000 news sources and blogs":"Ontvang zeldzaam nieuws, wereldwijde weersvoorspellingen en zoekartikelen van meer dan 30.000 nieuws en blogs","Only friends of friends can send friend request":"Alleen vrienden van vrienden kunnen vriendschapsverzoeken verzenden"}